astrobook/__init__.py
astrobook/core.py
astrobook-0.0.3.dist-info/LICENSE.txt
astrobook-0.0.3.dist-info/METADATA
astrobook-0.0.3.dist-info/WHEEL
astrobook-0.0.3.dist-info/top_level.txt
astrobook-0.0.3.dist-info/RECORD
