Metadata-Version: 2.1
Name: astrobook
Version: 0.0.3
Summary: A python package for astronomical calculations
Home-page: https://github.com/behrouzz/astrobook
Author: Behrouz Safari
Author-email: behrouz.safari@gmail.com
License: MIT
Classifier: Programming Language :: Python :: 3
Classifier: License :: OSI Approved :: MIT License
Classifier: Operating System :: OS Independent
Requires-Python: >=3.7
License-File: LICENSE.txt
Requires-Dist: numpy
Requires-Dist: pandas
Requires-Dist: requests
